monthinfo/__init__.py
monthinfo/monthinfo.py
tests/__init__.py
tests/test_month_info.py
monthinfo-2.0.0.dist-info/LICENSE
monthinfo-2.0.0.dist-info/METADATA
monthinfo-2.0.0.dist-info/WHEEL
monthinfo-2.0.0.dist-info/top_level.txt
monthinfo-2.0.0.dist-info/RECORD
