Metadata-Version: 2.1
Name: monthinfo
Version: 2.0.0
Summary: A collection of utility functions for working with a given month
Home-page: https://github.com/your_github_username/monthinfo
Author: Marco Ostaska
Author-email: marcoan@ymail.com
Classifier: Programming Language :: Python :: 3.9
Classifier: License :: OSI Approved :: MIT License
Classifier: Operating System :: OS Independent
Requires-Python: >=3.9
License-File: LICENSE
